whisperx_nemo_pipeline/__init__.py
whisperx_nemo_pipeline/helpers.py
whisperx_nemo_pipeline/transcription_pipeline.py
whisperx_nemo_pipeline/nemo_msdd_configs/diar_infer_general.yaml
whisperx_nemo_pipeline/nemo_msdd_configs/diar_infer_meeting.yaml
whisperx_nemo_pipeline/nemo_msdd_configs/diar_infer_telephonic.yaml
whisperx_nemo_pipeline/vendor/ctc-forced-aligner/README.md
whisperx_nemo_pipeline/vendor/ctc-forced-aligner/pyproject.toml
whisperx_nemo_pipeline/vendor/ctc-forced-aligner/requirements.txt
whisperx_nemo_pipeline/vendor/ctc-forced-aligner/setup.py
whisperx_nemo_pipeline/vendor/ctc-forced-aligner/ctc_forced_aligner/__init__.py
whisperx_nemo_pipeline/vendor/ctc-forced-aligner/ctc_forced_aligner/align.py
whisperx_nemo_pipeline/vendor/ctc-forced-aligner/ctc_forced_aligner/alignment_utils.py
whisperx_nemo_pipeline/vendor/ctc-forced-aligner/ctc_forced_aligner/forced_align_impl.cpp
whisperx_nemo_pipeline/vendor/ctc-forced-aligner/ctc_forced_aligner/norm_config.py
whisperx_nemo_pipeline/vendor/ctc-forced-aligner/ctc_forced_aligner/punctuations.lst
whisperx_nemo_pipeline/vendor/ctc-forced-aligner/ctc_forced_aligner/text_utils.py
whisperx_nemo_pipeline/vendor/ctc-forced-aligner/tests/test_alignment.py
whisperx_nemo_pipeline/vendor/whisperx_nemo_pipeline/deepmultilingualpunctuation/LICENSE
whisperx_nemo_pipeline/vendor/whisperx_nemo_pipeline/deepmultilingualpunctuation/README.md
whisperx_nemo_pipeline/vendor/whisperx_nemo_pipeline/deepmultilingualpunctuation/dev-readme.md
whisperx_nemo_pipeline/vendor/whisperx_nemo_pipeline/deepmultilingualpunctuation/setup.py
whisperx_nemo_pipeline/vendor/whisperx_nemo_pipeline/deepmultilingualpunctuation/deepmultilingualpunctuation/__init__.py
whisperx_nemo_pipeline/vendor/whisperx_nemo_pipeline/deepmultilingualpunctuation/deepmultilingualpunctuation/punctuationmodel.py
whisperx_nemo_pipeline/vendor/whisperx_nemo_pipeline/demucs/CODE_OF_CONDUCT.md
whisperx_nemo_pipeline/vendor/whisperx_nemo_pipeline/demucs/CONTRIBUTING.md
whisperx_nemo_pipeline-1.0.0.dist-info/licenses/LICENSE
whisperx_nemo_pipeline-1.0.0.dist-info/METADATA
whisperx_nemo_pipeline-1.0.0.dist-info/WHEEL
whisperx_nemo_pipeline-1.0.0.dist-info/top_level.txt
whisperx_nemo_pipeline-1.0.0.dist-info/RECORD
